consul_lock/__init__.py
consul_lock/defaults.py
consul_lock/lock_impl.py
consul_lock-0.1.6.dist-info/DESCRIPTION.rst
consul_lock-0.1.6.dist-info/METADATA
consul_lock-0.1.6.dist-info/metadata.json
consul_lock-0.1.6.dist-info/RECORD
consul_lock-0.1.6.dist-info/top_level.txt
consul_lock-0.1.6.dist-info/WHEEL
consul_lock-0.1.6.dist-info/zip-safe
