Metadata-Version: 2.0
Name: consul-lock
Version: 0.1.6
Summary: Distributed locking built on top of Consul.
Home-page: http://github.com/oysterbooks/python-consul-lock
Author: Oyster
Author-email: engineering@oysterbooks.com
License: MIT
Platform: UNKNOWN
Requires-Dist: python-consul
